xnano/__init__.py
xnano/_cli.py
xnano/agents.py
xnano/completions.py
xnano/data.py
xnano/generators.py
xnano/models.py
xnano/text.py
xnano/lib/__init__.py
xnano/lib/cache.py
xnano/lib/console.py
xnano/lib/exceptions.py
xnano/lib/repl.py
xnano/lib/router.py
xnano/resources/__init__.py
xnano/resources/agents/__init__.py
xnano/resources/agents/_routing.py
xnano/resources/agents/_routing.pyi
xnano/resources/agents/agent.py
xnano/resources/agents/agent.pyi
xnano/resources/agents/helpers.py
xnano/resources/agents/initializer.py
xnano/resources/agents/step.py
xnano/resources/agents/step.pyi
xnano/resources/completions/__init__.py
xnano/resources/completions/_routing.py
xnano/resources/completions/_routing.pyi
xnano/resources/completions/main.py
xnano/resources/completions/resources/__init__.py
xnano/resources/completions/resources/batch.py
xnano/resources/completions/resources/messages.py
xnano/resources/completions/resources/structured_outputs.py
xnano/resources/completions/resources/tool_calling.py
xnano/resources/completions/resources/utils.py
xnano/resources/data/__init__.py
xnano/resources/data/_routing.py
xnano/resources/data/_routing.pyi
xnano/resources/data/database.py
xnano/resources/data/vector_store.py
xnano/resources/data/web.py
xnano/resources/generators/__init__.py
xnano/resources/generators/_routing.py
xnano/resources/generators/_routing.pyi
xnano/resources/generators/chunker.py
xnano/resources/generators/classifier.py
xnano/resources/generators/code_generators.py
xnano/resources/generators/extractor.py
xnano/resources/generators/generate_sql.py
xnano/resources/generators/multimodal.py
xnano/resources/generators/prompting.py
xnano/resources/generators/question_answer.py
xnano/resources/generators/validator.py
xnano/resources/models/__init__.py
xnano/resources/models/document.py
xnano/resources/models/mixin.py
xnano/resources/models/mixin.pyi
xnano/resources/text/__init__.py
xnano/resources/text/_routing.py
xnano/resources/text/_routing.pyi
xnano-0.0.52.dist-info/METADATA
xnano-0.0.52.dist-info/WHEEL
xnano-0.0.52.dist-info/entry_points.txt
xnano-0.0.52.dist-info/licenses/LICENSE
xnano-0.0.52.dist-info/RECORD
