Metadata-Version: 2.3
Name: xnano
Version: 0.0.52
Summary: build extremely 'nano' llm workflows
Requires-Python: >=3.9
Requires-Dist: instructor>=1.6.3
Requires-Dist: litellm>=1.52.3
Requires-Dist: pypdf2>=3.0.1
Requires-Dist: qdrant-client>=1.12.1
Requires-Dist: questionary>=2.0.1
Requires-Dist: rich>=13.9.4
Requires-Dist: semchunk>=2.2.0
Requires-Dist: sqlalchemy>=2.0.36
Requires-Dist: tavily-python>=0.5.0
Provides-Extra: fastembed
Requires-Dist: fastembed>=0.4.1; extra == 'fastembed'
Provides-Extra: serve
Requires-Dist: fastapi; extra == 'serve'
Requires-Dist: nicegui; extra == 'serve'
Requires-Dist: sse-starlette; extra == 'serve'
Requires-Dist: uvicorn; extra == 'serve'
